naghelp/__init__.py
naghelp/collect.py
naghelp/host.py
naghelp/launcher.py
naghelp/mixins.py
naghelp/perf.py
naghelp/plugin.py
naghelp/response.py
naghelp/tools.py
python_nagios_helpers-0.2.3.dist-info/DESCRIPTION.rst
python_nagios_helpers-0.2.3.dist-info/METADATA
python_nagios_helpers-0.2.3.dist-info/RECORD
python_nagios_helpers-0.2.3.dist-info/WHEEL
python_nagios_helpers-0.2.3.dist-info/eager_resources.txt
python_nagios_helpers-0.2.3.dist-info/metadata.json
python_nagios_helpers-0.2.3.dist-info/top_level.txt
