Metadata-Version: 2.0
Name: python-nagios-helpers
Version: 0.2.3
Summary: Helper Classes for plugin development and nagios management.
Home-page: https://github.com/elapouya/python-nagios-helpers
Author: Eric Lapouyade
Author-email: elapouya@gmail.com
License: LGPL 2.1
Keywords: naghelp
Platform: UNKNOWN
Classifier: Intended Audience :: Developers
Classifier: Development Status :: 4 - Beta
Classifier: Programming Language :: Python :: 2
Classifier: Programming Language :: Python :: 2.7
Requires-Dist: Sphinx
Requires-Dist: sphinxcontrib-napoleon
Requires-Dist: paramiko
Requires-Dist: pexpect
Requires-Dist: python-textops
Requires-Dist: pysnmp
Requires-Dist: requests
